django_classified/__init__.py
django_classified/admin.py
django_classified/apps.py
django_classified/context_processors.py
django_classified/feeds.py
django_classified/forms.py
django_classified/models.py
django_classified/settings.py
django_classified/sitemap.py
django_classified/urls.py
django_classified/views.py
django_classified/locale/django.pot
django_classified/locale/ar/LC_MESSAGES/django.mo
django_classified/locale/ar/LC_MESSAGES/django.po
django_classified/locale/az/LC_MESSAGES/django.mo
django_classified/locale/az/LC_MESSAGES/django.po
django_classified/locale/de/LC_MESSAGES/django.mo
django_classified/locale/de/LC_MESSAGES/django.po
django_classified/locale/es/LC_MESSAGES/django.mo
django_classified/locale/es/LC_MESSAGES/django.po
django_classified/locale/fr/LC_MESSAGES/django.mo
django_classified/locale/fr/LC_MESSAGES/django.po
django_classified/locale/pl/LC_MESSAGES/django.mo
django_classified/locale/pl/LC_MESSAGES/django.po
django_classified/locale/pt/LC_MESSAGES/django.mo
django_classified/locale/pt/LC_MESSAGES/django.po
django_classified/locale/ru/LC_MESSAGES/django.mo
django_classified/locale/ru/LC_MESSAGES/django.po
django_classified/locale/tr/LC_MESSAGES/django.mo
django_classified/locale/tr/LC_MESSAGES/django.po
django_classified/locale/tr_TR/LC_MESSAGES/django.mo
django_classified/locale/tr_TR/LC_MESSAGES/django.po
django_classified/migrations/0001_initial.py
django_classified/migrations/0002_auto_20180713_2158.py
django_classified/migrations/0003_auto_20180717_1107.py
django_classified/migrations/__init__.py
django_classified/static/django_classified/css/bootstrap.min.css
django_classified/static/django_classified/css/bootstrap.min.css.map
django_classified/static/django_classified/css/jumbotron-narrow.css
django_classified/static/django_classified/css/lightbox.min.css
django_classified/static/django_classified/css/style.css
django_classified/static/django_classified/fonts/glyphicons-halflings-regular.eot
django_classified-1.1.2.dist-info/LICENSE.txt
django_classified-1.1.2.dist-info/METADATA
django_classified-1.1.2.dist-info/WHEEL
django_classified-1.1.2.dist-info/top_level.txt
django_classified-1.1.2.dist-info/RECORD
