Metadata-Version: 2.2
Name: django-classified
Version: 1.1.2
Summary: Django Classified
Home-page: https://github.com/slyapustin/django-classified
Author: Sergey Lyapustin
Author-email: s.lyapustin@gmail.com
Keywords: django classified
Classifier: Programming Language :: Python :: 3.9
Classifier: Programming Language :: Python :: 3.10
Classifier: Programming Language :: Python :: 3.11
Classifier: Programming Language :: Python :: 3.12
Classifier: Programming Language :: Python :: 3.13
Classifier: License :: OSI Approved :: MIT License
Classifier: Operating System :: OS Independent
Requires-Python: >=3.9
License-File: LICENSE.txt
Requires-Dist: django-bootstrap-form
Requires-Dist: django-filter
Requires-Dist: Django<5.2,>=4.2
Requires-Dist: Pillow
Requires-Dist: sorl-thumbnail
Requires-Dist: babel
Dynamic: author
Dynamic: author-email
Dynamic: classifier
Dynamic: description
Dynamic: description-content-type
Dynamic: home-page
Dynamic: keywords
Dynamic: requires-dist
Dynamic: requires-python
Dynamic: summary
